autofeedback2pr/__init__.py
autofeedback2pr/core.py
autofeedback2pr-0.2.0.dist-info/METADATA
autofeedback2pr-0.2.0.dist-info/WHEEL
autofeedback2pr-0.2.0.dist-info/top_level.txt
autofeedback2pr-0.2.0.dist-info/RECORD
