Metadata-Version: 2.1
Name: autofeedback2pr
Version: 0.2.0
Summary: Auto feedback classifier and grader for developer workflow.
Home-page: https://github.com/ITworkonline/autofeedback2pr
Author: ITworkonline
Author-email: jay123.studio@gmail.com
License: MIT
Platform: UNKNOWN
Requires-Python: >=3.7
Requires-Dist: requests
